[{"state":"FL","property_count":63},{"state":"CA","property_count":59},{"state":"TX","property_count":51},{"state":"GA","property_count":30},{"state":"NC","property_count":19},{"state":"NY","property_count":19},{"state":"TN","property_count":17},{"state":"OH","property_count":17},{"state":"MI","property_count":15},{"state":"PA","property_count":14},{"state":"AZ","property_count":14},{"state":"IL","property_count":13},{"state":"CO","property_count":12},{"state":"MO","property_count":12},{"state":"NJ","property_count":11},{"state":"MA","property_count":11},{"state":"WA","property_count":11},{"state":"MD","property_count":9},{"state":"VA","property_count":8},{"state":"SC","property_count":8},{"state":"AL","property_count":8},{"state":"NV","property_count":8},{"state":"KY","property_count":7},{"state":"CT","property_count":6},{"state":"KS","property_count":6},{"state":"OR","property_count":6},{"state":"WI","property_count":5},{"state":"MS","property_count":5},{"state":"LA","property_count":5},{"state":"MN","property_count":4},{"state":"OK","property_count":3},{"state":"IN","property_count":3},{"state":"AR","property_count":3},{"state":"UT","property_count":3},{"state":"IA","property_count":3},{"state":"ID","property_count":2},{"state":"WV","property_count":2},{"state":"MT","property_count":2},{"state":"DE","property_count":1},{"state":"SD","property_count":1},{"state":"ME","property_count":1},{"state":"HI","property_count":1},{"state":"NH","property_count":1},{"state":"AK","property_count":1}]